{
	"mochi": {
		"id": "mochi",
		"name": "Mochi",
		"species": "cat",
		"gender": "female",
		"description": "Una gata tranquila y cariñosa que adora los rincones soleados.",
		"appears_on_day": 1,
		"image_path": ""
	},
	"luna": {
		"id": "luna",
		"name": "Luna",
		"species": "dog",
		"gender": "female",
		"description": "Una perra juguetona y leal que siempre está lista para salir a pasear.",
		"appears_on_day": 2,
		"image_path": ""
	},
 	"canela": {
		"id": "canela",
		"name": "Canela",
		"species": "cat",
		"gender": "female",
		"description": "Una gata curiosa y elegante a la que le encanta explorar cada rincón.",
		"appears_on_day": 3,
		"image_path": ""
	},
	"nube": {
		"id": "nube",
		"name": "Nube",
		"species": "dog",
		"gender": "male",
		"description": "Un perro tranquilo y observador que disfruta de largas siestas.",
		"appears_on_day": 4,
		"image_path": ""
	}
}
